mrcnn/__init__.py
mrcnn/config.py
mrcnn/model.py
mrcnn/parallel_model.py
mrcnn/utils.py
mrcnn/visualize.py
mrcnn_tf115-0.0.2.dist-info/LICENSE
mrcnn_tf115-0.0.2.dist-info/METADATA
mrcnn_tf115-0.0.2.dist-info/WHEEL
mrcnn_tf115-0.0.2.dist-info/top_level.txt
mrcnn_tf115-0.0.2.dist-info/RECORD
